face_detector/__init__.py
face_detector/analyze.py
face_detector/detect.py
face_detector/interface.py
face_detector/models.py
face_detector/test.py
face_detector/train.py
face_detector/utils/__init__.py
face_detector/utils/augmentations.py
face_detector/utils/datasets.py
face_detector/utils/logger.py
face_detector/utils/parse_config.py
face_detector/utils/utils.py
Face_Detector_shu244-0.1.3.dist-info/METADATA
Face_Detector_shu244-0.1.3.dist-info/WHEEL
Face_Detector_shu244-0.1.3.dist-info/top_level.txt
Face_Detector_shu244-0.1.3.dist-info/RECORD
