Metadata-Version: 2.1
Name: Face-Detector-shu244
Version: 0.1.3
Summary: Extract faces from images
Home-page: UNKNOWN
Author: Shuhao Lai
Author-email: Shuhaolai18@gmail.com
License: UNKNOWN
Platform: UNKNOWN
Requires-Dist: opencv-python (==4.4.0.46)
Requires-Dist: torch (==1.6.0)
Requires-Dist: numpy (==1.19.1)
Requires-Dist: torchvision (==0.7.0)
Requires-Dist: matplotlib (==3.3.1)
Requires-Dist: Pillow (==8.0.1)
